wagtailcache/__init__.py
wagtailcache/apps.py
wagtailcache/cache.py
wagtailcache/settings.py
wagtailcache/urls.py
wagtailcache/views.py
wagtailcache/wagtail_hooks.py
wagtailcache/management/commands/clear_wagtail_cache.py
wagtailcache/templates/wagtailcache/index.html
wagtailcache/templates/wagtailcache/wagtailcache-bolt.svg
wagtailcache/templatetags/__init__.py
wagtailcache/templatetags/wagtailcache_tags.py
cjkcms_cache-2.3.2.dist-info/LICENSE
cjkcms_cache-2.3.2.dist-info/METADATA
cjkcms_cache-2.3.2.dist-info/WHEEL
cjkcms_cache-2.3.2.dist-info/top_level.txt
cjkcms_cache-2.3.2.dist-info/RECORD
