Metadata-Version: 2.1
Name: cjkcms-cache
Version: 2.3.2
Summary: A simple page cache for Wagtail based on the Django cache middleware. Forked from wagtail-cache.
Home-page: https://github.com/cjkpl/cjkcms-cache
Author: Grzegorz Krol
Author-email: info@cjkcms.com
License: BSD license
Classifier: Intended Audience :: Developers
Classifier: License :: OSI Approved :: BSD License
Classifier: Natural Language :: English
Classifier: Operating System :: OS Independent
Classifier: Programming Language :: Python :: 3
Classifier: Programming Language :: Python :: 3 :: Only
Classifier: Framework :: Django
Classifier: Framework :: Wagtail
Classifier: Framework :: Wagtail :: 3
Classifier: Framework :: Wagtail :: 4
Classifier: Framework :: Wagtail :: 5
License-File: LICENSE
Requires-Dist: wagtail <7,>=3.0
